{
  "packages": {
    ".": {
      "package-name": "vesper",
      "changelog-path": "docs/CHANGELOG.md",
      "release-type": "ruby",
      "extra-files": [
        "lib/core/version.rb"
      ]
    }
  },
  "changelog-sections": [
    { "type": "feat", "section": "Features" },
    { "type": "fix", "section": "Bug Fixes" },
    { "type": "perf", "section": "Performance Improvements" },
    { "type": "docs", "section": "Documentation" },
    { "type": "refactor", "section": "Code Refactoring" }
  ],
  "skip-labeling": true
}
